mpcorbfile/__init__.py
mpcorbfile/cli.py
mpcorbfile/mpcorbfile.py
mpcorbfile-1.0.4.dist-info/AUTHORS.rst
mpcorbfile-1.0.4.dist-info/LICENSE
mpcorbfile-1.0.4.dist-info/METADATA
mpcorbfile-1.0.4.dist-info/WHEEL
mpcorbfile-1.0.4.dist-info/entry_points.txt
mpcorbfile-1.0.4.dist-info/RECORD
